connectfourmd/Connectfour.py
connectfourmd/__init__.py
connectfourmd/__main__.py
connectfourmd-1.0.0.dist-info/METADATA
connectfourmd-1.0.0.dist-info/WHEEL
connectfourmd-1.0.0.dist-info/entry_points.txt
connectfourmd-1.0.0.dist-info/top_level.txt
connectfourmd-1.0.0.dist-info/RECORD
