Metadata-Version: 2.4
Name: connectfourmd
Version: 1.0.0
Summary: connect four game using pygame
Author-email: Maalek Darkal <maalekdarkal@gmail.com>
License: MIT
Project-URL: Homepage, https://github.com/MaalekDarkalX1/connectfourmd
Classifier: Programming Language :: Python :: 3
Classifier: License :: OSI Approved :: MIT License
Classifier: Operating System :: OS Independent
Classifier: Topic :: Games/Entertainment
Requires-Python: >=3.8
